README.rst
setup.py
multinet/__init__.py
multinet/bipartite.py
multinet/builder.py
multinet/classes.py
multinet/information_measure.py
multinet/l_core.py
multinet/random_models.py
multinet/shortest_path.py
multinet.egg-info/PKG-INFO
multinet.egg-info/SOURCES.txt
multinet.egg-info/dependency_links.txt
multinet.egg-info/requires.txt
multinet.egg-info/top_level.txt
multinet/tests/test_bipartite.py
multinet/tests/test_classes.py
multinet/tests/test_information_measure.py
multinet/tests/test_random_models.py
multinet/tests/test_shortest_path.py
multinet/util/__init__.py
multinet/util/filter_helper.py
multinet/util/layer_helper.py
multinet/util/weight_helper.py