Metadata-Version: 1.0
Name: multinet
Version: 0.1
Summary: Networkx extension for multiplex networks
Home-page: UNKNOWN
Author: Haochen Wu
Author-email: multinet@haochenwu.com
License: UNKNOWN
Platform: UNKNOWN
